sdk-timeular-tools/__init__.py
timeular/__init__.py
timeular/timeular.py
sdk_timeular_tools-0.1.dist-info/LICENSE
sdk_timeular_tools-0.1.dist-info/METADATA
sdk_timeular_tools-0.1.dist-info/WHEEL
sdk_timeular_tools-0.1.dist-info/top_level.txt
sdk_timeular_tools-0.1.dist-info/RECORD
