Metadata-Version: 2.1
Name: sdk-timeular-tools
Version: 0.1
Summary: A python wrapper around the Timeular HTTP API, and some notebooks of questionable usefulness
Home-page: http://github.com/davidbstein/sdk-timeular-tools
Author: stein
Author-email: sdk-timeular-tools-pypi@emailcatcher.xyz
License: MIT
Platform: UNKNOWN
Classifier: Development Status :: 3 - Alpha
Classifier: Environment :: MacOS X
Classifier: Programming Language :: Python :: 3.9
Classifier: Topic :: Software Development :: Libraries :: Python Modules
